hayes/__init__.py
hayes/conn.py
hayes/importing.py
hayes/indexing.py
hayes/models.py
hayes/transport.py
hayes/utils.py
hayes/analysis/__init__.py
hayes/django_interop/__init__.py
hayes/django_interop/base.py
hayes/ext/__init__.py
hayes/ext/date_tail.py
hayes/ext/stopwords.py
hayes/ext/word_gatherer.py
hayes/search/__init__.py
hayes/search/filters.py
hayes/search/highlight.py
hayes/search/internal.py
hayes/search/queries.py
hayes-0.1.0.dist-info/DESCRIPTION.rst
hayes-0.1.0.dist-info/LICENSE.txt
hayes-0.1.0.dist-info/METADATA
hayes-0.1.0.dist-info/RECORD
hayes-0.1.0.dist-info/WHEEL
hayes-0.1.0.dist-info/metadata.json
hayes-0.1.0.dist-info/top_level.txt
